first_package/__init__.py
first_package/main.py
xmars-1.0.0.dist-info/LICENSE
xmars-1.0.0.dist-info/METADATA
xmars-1.0.0.dist-info/WHEEL
xmars-1.0.0.dist-info/top_level.txt
xmars-1.0.0.dist-info/RECORD
