Metadata-Version: 2.1
Name: xmars
Version: 1.0.0
Summary: Prepare for something awesome
Home-page: https://github.com/xmars4
Author: XMars
Author-email: xtruongptit@gmail.com
License: UNKNOWN
Project-URL: Bug Tracker, https://github.com/xmars4
Platform: UNKNOWN
Classifier: Programming Language :: Python :: 3
Classifier: License :: OSI Approved :: MIT License
Classifier: Operating System :: OS Independent
Requires-Python: >=3.6
License-File: LICENSE
